sql_face/__init__.py
sql_face/_modidx.py
sql_face/alchemy.py
sql_face/codeformer.py
sql_face/core.py
sql_face/databases.py
sql_face/faceangles.py
sql_face/qmagface.py
sql_face/serfiq.py
sql_face/sqldb.py
sql_face/sr_utils.py
sql_face/tables.py
sql_face/tface.py
sql_face-0.1.16.dist-info/LICENSE
sql_face-0.1.16.dist-info/METADATA
sql_face-0.1.16.dist-info/WHEEL
sql_face-0.1.16.dist-info/entry_points.txt
sql_face-0.1.16.dist-info/top_level.txt
sql_face-0.1.16.dist-info/RECORD
